PyDX/__init__.py
PyDX/pydx.py
PyDX_DevWorks8-1.0.0.dist-info/LICENSE
PyDX_DevWorks8-1.0.0.dist-info/METADATA
PyDX_DevWorks8-1.0.0.dist-info/WHEEL
PyDX_DevWorks8-1.0.0.dist-info/top_level.txt
PyDX_DevWorks8-1.0.0.dist-info/RECORD
