Metadata-Version: 2.1
Name: PyDX-DevWorks8
Version: 1.0.0
Summary: Flatten and inflate a dictionary
Home-page: https://github.com/Devworks8/PyDX.git
Author: Christian Lachapelle
Author-email: devworks8@gmail.com
License: UNKNOWN
Platform: UNKNOWN
Classifier: Programming Language :: Python :: 3
Classifier: License :: OSI Approved :: GNU General Public License v3 (GPLv3)
Classifier: Operating System :: OS Independent
Requires-Python: >=3.6
